jackie/__init__.py
jackie/bridge.py
jackie/client.py
jackie/http/__init__.py
jackie/http/cookie.py
jackie/http/exceptions.py
jackie/http/request.py
jackie/http/response.py
jackie/http/socket.py
jackie/http/stream.py
jackie/http/wrappers.py
jackie/multidict.py
jackie/multipart.py
jackie/parse.py
jackie/router/__init__.py
jackie/router/matcher.py
jackie/router/router.py
jackie/serialize.py
jackie-0.2.0.dist-info/LICENSE.txt
jackie-0.2.0.dist-info/WHEEL
jackie-0.2.0.dist-info/METADATA
jackie-0.2.0.dist-info/RECORD
