Metadata-Version: 2.1
Name: jackie
Version: 0.2.0
Summary: A minimal ASGI web framework.
License: MIT
Author: Daan van der Kallen
Author-email: mail@daanvdk.com
Requires-Python: >=3.6,<4.0
Classifier: License :: OSI Approved :: MIT License
Classifier: Programming Language :: Python :: 3
Classifier: Programming Language :: Python :: 3.6
Classifier: Programming Language :: Python :: 3.7
Classifier: Programming Language :: Python :: 3.8
Classifier: Programming Language :: Python :: 3.9
Requires-Dist: asgiref (>=3.3.1,<4.0.0)
